{
  "version": "2.0",
  "envId": "chunxiao-d8ghfaw3y0781da11",
  "functions": [
    {
      "name": "dbProxy",
      "runtime": "Nodejs18.15",
      "handler": "index.main",
      "timeout": 30,
      "triggers": [],
      "params": {
        "enablePublicAccess": true
      },
      "envVariables": {
        "DB_PROXY_API_KEY": "chunxiao-dbproxy-2026",
        "SERVERCHAN_KEY": ""
      }
    },
    {
      "name": "verify-code",
      "runtime": "Nodejs18.15",
      "handler": "index.main",
      "timeout": 20,
      "triggers": [],
      "params": {
        "enablePublicAccess": true
      },
      "envVariables": {
        "EMAIL_USER": "",
        "EMAIL_PASS": ""
      }
    }
  ]
}